waffles/__init__.py
waffles/__main__.py
waffles/baker.py
waffles/sprinkles.py
waffles/waffle.py
waffles-0.0.4.dist-info/WHEEL
waffles-0.0.4.dist-info/METADATA
waffles-0.0.4.dist-info/RECORD
